{"nodes":[{"id":"Note 1 regarding topic 1","path":"/explorer-hugo-theme/notes/topic-1-note-1/","label":"Note 1 regarding topic 1","number_neighbours":0},{"id":"Isolated note 1 regarding topic 3","path":"/explorer-hugo-theme/notes/topic-3-note-1/","label":"Isolated note 1 regarding topic 3","number_neighbours":0},{"id":"Note 1 regarding topic 2","path":"/explorer-hugo-theme/notes/topic-2-note-1/","label":"Note 1 regarding topic 2","number_neighbours":1},{"id":"Note 2 regarding topic 1","path":"/explorer-hugo-theme/notes/topic-1-note-2/","label":"Note 2 regarding topic 1","number_neighbours":1},{"id":"Note 2 regarding topic 2","path":"/explorer-hugo-theme/notes/topic-2-note-2/","label":"Note 2 regarding topic 2","number_neighbours":1},{"id":"Sample Post 1","path":"/explorer-hugo-theme/posts/post-1/","label":"Sample Post 1","number_neighbours":0},{"id":"Shortcode for Columns","path":"/explorer-hugo-theme/notes/shortcode-for-columns/","label":"Shortcode for Columns","number_neighbours":1},{"id":"Shortcode for Details","path":"/explorer-hugo-theme/notes/shortcode-for-details/","label":"Shortcode for Details","number_neighbours":1},{"id":"Shortcode for Hints","path":"/explorer-hugo-theme/notes/shortcode-for-hints/","label":"Shortcode for Hints","number_neighbours":1},{"id":"Shortcode for Mermaid","path":"/explorer-hugo-theme/notes/shortcode-for-mermaid/","label":"Shortcode for Mermaid","number_neighbours":1},{"id":"Shortcode for Tabs","path":"/explorer-hugo-theme/notes/shortcode-for-tabs/","label":"Shortcode for Tabs","number_neighbours":1},{"id":"Shortcodes","path":"/explorer-hugo-theme/notes/shortcodes/","label":"Shortcodes","number_neighbours":0}],"edges":[{"source":"Note 1 regarding topic 2","target":"Note 1 regarding topic 1"},{"source":"Note 2 regarding topic 1","target":"Note 1 regarding topic 1"},{"source":"Note 2 regarding topic 2","target":"Note 1 regarding topic 2"},{"source":"Shortcode for Columns","target":"Shortcodes"},{"source":"Shortcode for Details","target":"Shortcodes"},{"source":"Shortcode for Hints","target":"Shortcodes"},{"source":"Shortcode for Mermaid","target":"Shortcodes"},{"source":"Shortcode for Tabs","target":"Shortcodes"}]}